{
  "setting": {},
  "condition": {
    "plugin": {
      "list": []
    },
    "game": {
      "list": []
    },
    "gamePlugin": {
      "list": []
    },
    "miniprogram": {
      "list": [
        {
          "name": "pages/category/index",
          "pathName": "pages/category/index",
          "query": "",
          "scene": null
        },
        {
          "name": "pages/index/index",
          "pathName": "pages/index/index",
          "query": "",
          "scene": null
        },
        {
          "name": "pages/goods_list/index",
          "pathName": "pages/goods_list/index",
          "query": "id=5",
          "scene": null
        },
        {
          "name": "pages/goods_detail/index",
          "pathName": "pages/goods_detail/index",
          "query": "",
          "scene": null
        },
        {
          "name": "pages/cart/index",
          "pathName": "pages/cart/index",
          "query": "",
          "scene": null
        },
        {
          "name": "pages/index/index",
          "pathName": "pages/index/index",
          "query": "",
          "scene": null
        },
        {
          "name": "pages/auth/index",
          "pathName": "pages/auth/index",
          "query": "",
          "scene": null
        },
        {
          "name": "pages/login/index",
          "pathName": "pages/login/index",
          "query": "",
          "scene": null
        },
        {
          "name": "pages/user/index",
          "pathName": "pages/user/index",
          "query": "",
          "scene": null
        },
        {
          "name": "pages/order/index",
          "pathName": "pages/order/index",
          "query": "type=1",
          "scene": null
        },
        {
          "name": "pages/collect/index",
          "pathName": "pages/collect/index",
          "query": "",
          "scene": null
        },
        {
          "name": "pages/search/index",
          "pathName": "pages/search/index",
          "query": "",
          "scene": null
        },
        {
          "name": "pages/pay/index",
          "pathName": "pages/pay/index",
          "query": "type=1",
          "scene": null
        },
        {
          "name": "pages/site/site",
          "pathName": "pages/site/site",
          "query": "",
          "scene": null
        },
        {
          "name": "pages/addsite/addsite",
          "pathName": "pages/addsite/addsite",
          "query": "",
          "scene": null
        },
        {
          "name": "pages/goods_detail/index",
          "pathName": "pages/goods_detail/index",
          "query": "goods_id=17927",
          "scene": null
        }
      ]
    }
  }
}